app/__init__.py
app/admin.py
app/apps.py
app/models.py
app/tests.py
app/views.py
app/migrations/0001_initial.py
app/migrations/__init__.py
secret_message/__init__.py
secret_msg/__init__.py
secret_msg/asgi.py
secret_msg/settings.py
secret_msg/urls.py
secret_msg/wsgi.py
secret_message-1.0.dist-info/LICENSE.txt
secret_message-1.0.dist-info/METADATA
secret_message-1.0.dist-info/WHEEL
secret_message-1.0.dist-info/top_level.txt
secret_message-1.0.dist-info/RECORD
