Metadata-Version: 2.1
Name: secret-message
Version: 1.0
Summary: Create and share a Message Secretly.
Home-page: UNKNOWN
Author: E Lusifa Taehyung
Author-email: purplebird7613@gmail.com
License: UNKNOWN
Platform: UNKNOWN
Classifier: Programming Language :: Python
Classifier: License :: OSI Approved :: MIT License
Classifier: Operating System :: OS Independent
License-File: LICENSE.txt
